pyomop/CreateCohortTable.sql
pyomop/__init__.py
pyomop/__main__.py
pyomop/engine_factory.py
pyomop/eunomia.py
pyomop/llm_engine.py
pyomop/llm_query.py
pyomop/loader.py
pyomop/main.py
pyomop/mapping.default.json
pyomop/pyhealth.py
pyomop/sqldict.py
pyomop/vector.py
pyomop/vocabulary.py
pyomop/cdm54/__init__.py
pyomop/cdm54/cdm54_tables.py
pyomop/cdm6/__init__.py
pyomop/cdm6/cdm6_tables.py
pyomop/mcp/__init__.py
pyomop/mcp/__main__.py
pyomop/mcp/server.py
pyomop-6.3.0.dist-info/METADATA
pyomop-6.3.0.dist-info/WHEEL
pyomop-6.3.0.dist-info/entry_points.txt
pyomop-6.3.0.dist-info/licenses/AUTHORS.md
pyomop-6.3.0.dist-info/licenses/LICENSE
pyomop-6.3.0.dist-info/RECORD
