Metadata-Version: 2.4
Name: pyomop
Version: 6.3.0
Summary: OMOP CDM utils in Python
Project-URL: Homepage, https://dermatologist.github.io/pyomop/
Project-URL: Repository, https://github.com/dermatologist/pyomop
Project-URL: Documentation, https://dermatologist.github.io/pyomop/
Author-email: Bell Eapen <github_public@gulfdoctor.net>
License-File: AUTHORS.md
License-File: LICENSE
Keywords: python
Classifier: Development Status :: 4 - Beta
Classifier: Intended Audience :: Healthcare Industry
Classifier: Operating System :: OS Independent
Classifier: Programming Language :: Python
Classifier: Programming Language :: Python :: 3
Classifier: Programming Language :: Python :: 3.11
Classifier: Programming Language :: Python :: 3.12
Classifier: Topic :: Scientific/Engineering :: Information Analysis
Classifier: Topic :: Scientific/Engineering :: Medical Science Apps.
Classifier: Topic :: Software Development :: Libraries :: Python Modules
Requires-Python: <4.0,>=3.11
Requires-Dist: aiosqlite
Requires-Dist: asyncpg
Requires-Dist: click
Requires-Dist: fhiry>=5.1.1
Requires-Dist: greenlet
Requires-Dist: mcp
Requires-Dist: nest-asyncio
Requires-Dist: pandas
Requires-Dist: requests
Requires-Dist: sqlalchemy>=1.4
Provides-Extra: http
Requires-Dist: starlette; extra == 'http'
Requires-Dist: uvicorn; extra == 'http'
Provides-Extra: llm
Requires-Dist: dhti-elixir-base; extra == 'llm'
Requires-Dist: langchain-community; extra == 'llm'
Requires-Dist: langchain-core; extra == 'llm'
Requires-Dist: langchain-google-genai; extra == 'llm'
Requires-Dist: langchain-huggingface; extra == 'llm'
Requires-Dist: langchain-openai; extra == 'llm'
Requires-Dist: langchain>=1.0; extra == 'llm'
